{
    
    "generatemiaoratio": 1,
    "shootershootratio": 1,
    "shooterlowestattackspeedratio": 1,

    "initsun": 3000,
    "initmiaomode": "all",
    "initmiaorandomnummode": "FlowerPeng",
    "gamechecktime": 180,
    
    "initpeng": 8,
    "allowmiaolist": [
        "SunFlower", "JianGuo", "Cherry", 
        "YangTao", "PeaDouble"
    ],
    
    "initshooter": "YangTao",
    "initmiaolist": [
        "SunFlower", "SunFlower", "YangTao", "Cherry"
    ],
    "enmyspeedattackscale": 1,
    "enmyspeedmovescale": 2,
    "enmyviewscale": 0.68,
    "enmybehurtscale": 5.0,

    "enmys": {
        "4": [
            {
                "types": [ "zombi_s", "zombi_s", "zombi_s", "zombi_s", "zombi_s", "zombi_s", "zombi_s", "zombi_s", "zombi_s", "zombi_s" ],
                "typesmode": "next",
                "generator": [ 1, 2, 3, 4, 5, 6, 7, 8, 9, 10 ],
                "generatormode": "next",
                "lazyme": 0
            }
        ],
        "8": [
            {
                "types": [ "zombi_s", "zombi_s", "zombi_s", "zombi_s", "zombi_s", "zombi_s", "zombi_s", "zombi_s", "zombi_s", "zombi_s" ],
                "typesmode": "next",
                "generator": [ 1, 2, 3, 4, 5, 6, 7, 8, 9, 10 ],
                "generatormode": "next",
                "lazyme": 0
            }
        ],
        "12": [
            {
                "types": [ "zombi_s", "zombi_s", "zombi_s", "zombi_s", "zombi_s", "zombi_s", "zombi_s", "zombi_s", "zombi_s", "zombi_s" ],
                "typesmode": "next",
                "generator": [ 1, 2, 3, 4, 5, 6, 7, 8, 9, 10 ],
                "generatormode": "next",
                "lazyme": 0
            }
        ],
        "16": [
            {
                "types": [ "zombi_s", "zombi_s", "zombi_s", "zombi_s", "zombi_s", "zombi_s", "zombi_s", "zombi_s", "zombi_s", "zombi_s" ],
                "typesmode": "next",
                "generator": [ 1, 2, 3, 4, 5, 6, 7, 8, 9, 10 ],
                "generatormode": "random",
                "lazyme": 4
            }
        ],
        "20": [
            {
                "types": [ "zombi_s", "zombi_s", "zombi_s", "zombi_s", "zombi_s", "zombi_s", "zombi_s", "zombi_s", "zombi_s", "zombi_s" ],
                "typesmode": "next",
                "generator": [ 1, 2, 3, 4, 5, 6, 7, 8, 9, 10 ],
                "generatormode": "random",
                "lazyme": 0
            }
        ],
        "24": [
            {
                "types": [ "zombi_s", "zombi_s", "zombi_s", "zombi_s", "zombi_s", "zombi_s", "zombi_s", "zombi_s", "zombi_s", "zombi_s" ],
                "typesmode": "next",
                "generator": [ 1, 2, 3, 4, 5, 6, 7, 8, 9, 10 ],
                "generatormode": "random",
                "lazyme": 2
            }
        ],
        "40": [
            {
                "types": [ "zombi_mu_tong", "zombi_mu_tong", "zombi_mu_tong", "zombi_mu_tong", "zombi_mu_tong", "zombi_mu_tong", "zombi_mu_tong", "zombi_mu_tong", "zombi_mu_tong", "zombi_mu_tong" ],
                "typesmode": "next",
                "generator": [ 1, 2, 3, 4, 5, 6, 7, 8, 9, 10 ],
                "generatormode": "random",
                "lazyme": 0.5
            }
        ],
        "46": [
            {
                "types": [ "zombi_mu_tong", "zombi_mu_tong", "zombi_mu_tong", "zombi_mu_tong", "zombi_mu_tong", "zombi_mu_tong", "zombi_mu_tong", "zombi_mu_tong", "zombi_mu_tong", "zombi_mu_tong" ],
                "typesmode": "next",
                "generator": [ 1, 2, 3, 4, 5, 6, 7, 8, 9, 10 ],
                "generatormode": "random",
                "lazyme": 0.5
            }
        ],
        "52": [
            {
                "types": [ "zombi_mu_tong", "zombi_mu_tong", "zombi_mu_tong", "zombi_mu_tong", "zombi_mu_tong", "zombi_mu_tong", "zombi_mu_tong", "zombi_mu_tong", "zombi_mu_tong", "zombi_mu_tong" ],
                "typesmode": "next",
                "generator": [ 1, 2, 3, 4, 5, 6, 7, 8, 9, 10 ],
                "generatormode": "random",
                "lazyme": 0.5
            }
        ],
        "58": [
            {
                "types": [ "zombi_mu_tong", "zombi_mu_tong", "zombi_mu_tong", "zombi_mu_tong", "zombi_mu_tong", "zombi_mu_tong", "zombi_mu_tong", "zombi_mu_tong", "zombi_mu_tong", "zombi_mu_tong" ],
                "typesmode": "next",
                "generator": [ 1, 2, 3, 4, 5, 6, 7, 8, 9, 10 ],
                "generatormode": "random",
                "lazyme": 2
            }
        ],
        "64": [
            {
                "types": [ "zombi_mu_tong", "zombi_mu_tong", "zombi_mu_tong", "zombi_mu_tong", "zombi_mu_tong", "zombi_mu_tong", "zombi_mu_tong", "zombi_mu_tong", "zombi_mu_tong", "zombi_mu_tong" ],
                "typesmode": "next",
                "generator": [ 1, 2, 3, 4, 5, 6, 7, 8, 9, 10 ],
                "generatormode": "random",
                "lazyme": 0.5
            }
        ],
        "70": [
            {
                "types": [ "zombi_mu_tong", "zombi_mu_tong", "zombi_mu_tong", "zombi_mu_tong", "zombi_mu_tong", "zombi_mu_tong", "zombi_mu_tong", "zombi_mu_tong", "zombi_mu_tong", "zombi_mu_tong" ],
                "typesmode": "next",
                "generator": [ 1, 2, 3, 4, 5, 6, 7, 8, 9, 10 ],
                "generatormode": "random",
                "lazyme": 2
            }
        ],
        "76": [
            {
                "types": [ "zombi_s", "zombi_s", "zombi_s", "zombi_s", "zombi_s", "zombi_s", "zombi_s", "zombi_s", "zombi_s", "zombi_s" ],
                "typesmode": "next",
                "generator": [ 1, 2, 3, 4, 5, 6, 7, 8, 9, 10 ],
                "generatormode": "random",
                "lazyme": 0.5
            }
        ],
        "90": [
            {
                "types": [ "zombi_tie_tong", "zombi_tie_tong", "zombi_tie_tong", "zombi_tie_tong", "zombi_tie_tong", "zombi_tie_tong", "zombi_tie_tong", "zombi_tie_tong", "zombi_tie_tong", "zombi_tie_tong" ],
                "typesmode": "next",
                "generator": [ 1, 2, 3, 4, 5, 6, 7, 8, 9, 10 ],
                "generatormode": "random",
                "lazyme": 0
            }
        ],
        "100": [
            {
                "types": [ "zombi_tie_tong", "zombi_tie_tong", "zombi_tie_tong", "zombi_tie_tong", "zombi_tie_tong", "zombi_tie_tong", "zombi_tie_tong", "zombi_tie_tong", "zombi_tie_tong", "zombi_tie_tong" ],
                "typesmode": "next",
                "generator": [ 1, 2, 3, 4, 5, 6, 7, 8, 9, 10 ],
                "generatormode": "random",
                "lazyme": 0
            }
        ],
        "110": [
            {
                "types": [ "zombi_tie_tong", "zombi_tie_tong", "zombi_tie_tong", "zombi_tie_tong", "zombi_tie_tong", "zombi_tie_tong", "zombi_tie_tong", "zombi_tie_tong", "zombi_tie_tong", "zombi_tie_tong" ],
                "typesmode": "next",
                "generator": [ 1, 2, 3, 4, 5, 6, 7, 8, 9, 10 ],
                "generatormode": "random",
                "lazyme": 0
            }
        ],
        "115": [
            {
                "types": [ "zombi_tie_tong", "zombi_tie_tong", "zombi_tie_tong", "zombi_tie_tong", "zombi_tie_tong", "zombi_tie_tong", "zombi_tie_tong", "zombi_tie_tong", "zombi_tie_tong", "zombi_tie_tong" ],
                "typesmode": "next",
                "generator": [ 1, 2, 3, 4, 5, 6, 7, 8, 9, 10 ],
                "generatormode": "random",
                "lazyme": 0
            }
        ],
        "120": [
            {
                "types": [ "zombi_tie_tong", "zombi_tie_tong", "zombi_tie_tong", "zombi_tie_tong", "zombi_tie_tong", "zombi_tie_tong", "zombi_tie_tong", "zombi_tie_tong", "zombi_tie_tong", "zombi_tie_tong" ],
                "typesmode": "next",
                "generator": [ 1, 2, 3, 4, 5, 6, 7, 8, 9, 10 ],
                "generatormode": "random",
                "lazyme": 0
            }
        ],
        "130": [
            {
                "types": [ "zombi_tie_tong", "zombi_tie_tong", "zombi_tie_tong", "zombi_tie_tong", "zombi_tie_tong", "zombi_tie_tong", "zombi_tie_tong", "zombi_tie_tong", "zombi_tie_tong", "zombi_tie_tong" ],
                "typesmode": "next",
                "generator": [ 1, 2, 3, 4, 5, 6, 7, 8, 9, 10 ],
                "generatormode": "random",
                "lazyme": 0
            }
        ],
        "135": [
            {
                "types": [ "zombi_s", "zombi_s", "zombi_s", "zombi_s", "zombi_s", "zombi_s", "zombi_s", "zombi_s", "zombi_s", "zombi_s" ],
                "typesmode": "next",
                "generator": [ 1, 2, 3, 4, 5, 6, 7, 8, 9, 10 ],
                "generatormode": "random",
                "lazyme": 3
            }
        ],
        "140": [
            {
                "types": [ "zombi_s", "zombi_s", "zombi_s", "zombi_s", "zombi_s", "zombi_s", "zombi_s", "zombi_s", "zombi_s", "zombi_s" ],
                "typesmode": "next",
                "generator": [ 1, 2, 3, 4, 5, 6, 7, 8, 9, 10 ],
                "generatormode": "random",
                "lazyme": 2
            }
        ],
        "142": [
            {
                "types": [ "zombi_m", "zombi_m", "zombi_m", "zombi_m", "zombi_m", "zombi_m", "zombi_m", "zombi_m", "zombi_m", "zombi_m" ],
                "typesmode": "next",
                "generator": [ 1, 2, 3, 4, 5, 6, 7, 8, 9, 10 ],
                "generatormode": "random",
                "lazyme": 0
            }
        ],
        "150": [
            {
                "types": [ "zombi_s", "zombi_s", "zombi_s", "zombi_s", "zombi_s", "zombi_s", "zombi_s", "zombi_s", "zombi_s", "zombi_s" ],
                "typesmode": "next",
                "generator": [ 1, 2, 3, 4, 5, 6, 7, 8, 9, 10 ],
                "generatormode": "random",
                "lazyme": 0
            }
        ],
        "160": [
            {
                "types": [ "zombi_s", "zombi_s", "zombi_s", "zombi_s", "zombi_s", "zombi_s", "zombi_s", "zombi_s", "zombi_s", "zombi_s" ],
                "typesmode": "next",
                "generator": [ 1, 2, 3, 4, 5, 6, 7, 8, 9, 10 ],
                "generatormode": "random",
                "lazyme": 2
            }
        ],
        "165": [
            {
                "types": [ "zombi_s", "zombi_s", "zombi_s", "zombi_s", "zombi_s", "zombi_s", "zombi_s", "zombi_s", "zombi_s", "zombi_s" ],
                "typesmode": "next",
                "generator": [ 1, 2, 3, 4, 5, 6, 7, 8, 9, 10 ],
                "generatormode": "random",
                "lazyme": 1
            }
        ],
        "170": [
            {
                "types": [ "zombi_tie_tong", "zombi_tie_tong", "zombi_tie_tong", "zombi_tie_tong", "zombi_tie_tong", "zombi_tie_tong", "zombi_tie_tong", "zombi_tie_tong", "zombi_tie_tong", "zombi_tie_tong" ],
                "typesmode": "next",
                "generator": [ 1, 2, 3, 4, 5, 6, 7, 8, 9, 10 ],
                "generatormode": "random",
                "lazyme": 2
            }
        ],
        "175": [
            {
                "types": [ "zombi_tie_tong", "zombi_tie_tong", "zombi_tie_tong", "zombi_tie_tong", "zombi_tie_tong", "zombi_tie_tong", "zombi_tie_tong", "zombi_tie_tong", "zombi_tie_tong", "zombi_tie_tong" ],
                "typesmode": "next",
                "generator": [ 1, 2, 3, 4, 5, 6, 7, 8, 9, 10 ],
                "generatormode": "random",
                "lazyme": 0
            }
        ]
    }
}