{
    "type": "normal",
    "initsun": 200,
    "initmiaomode": "all",
    "initmiaorandomnummode": "FlowerPeng",
    "initmiaolist": [
        "Pea", "SunFlower", "SunFlower", "Cherry"
    ],
    "gamechecktime": 100,
    
    "initpeng": 8,

    "enmyswaveflag": {
        "19": 1
    },
    "enmys": {
        "4": [
            {
                "types": [ "zombi_s", "zombi_s", "zombi_s" ],
                "typesmode": "next",
                "generator": [ 3, 1, 5 ],
                "generatormode": "random",
                "lazyall": 0,
                "lazyme": 0.5,
                "speedmode": "normal"
            }
        ],
        "6": [
            {
                "types": [ "zombi_s", "zombi_s", "zombi_s", "zombi_s", "zombi_s", "zombi_s" ],
                "typesmode": "next",
                "generator": [ 9, 2, 8, 6, 4, 10 ],
                "generatormode": "next",
                "lazyall": 0,
                "lazyme": 3,
                "speedmode": "normal"
            }
        ],
        "18": [
            {
                "types": [ "zombi_mu_tong", "zombi_mu_tong", "zombi_mu_tong", "zombi_mu_tong", "zombi_mu_tong", "zombi_mu_tong" ],
                "typesmode": "next",
                "generator": [ 3, 7, 9, 4, 1, 6 ],
                "generatormode": "random",
                "lazyall": 0,
                "lazyme": 2,
                "speedmode": "normal"
            }
        ],
        "24": [
            {
                "types": [ "zombi_mu_tong", "zombi_mu_tong", "zombi_tie_tong", "zombi_mu_tong", "zombi_mu_tong", "zombi_mu_tong" ],
                "typesmode": "random",
                "generator": [ 2, 4, 10, 1, 5, 8 ],
                "generatormode": "random",
                "lazyall": 0,
                "lazyme": 2,
                "speedmode": "normal"
            }
        ],
        "30": [
            {
                "types": [ "zombi_s", "zombi_s", "zombi_s", "zombi_s", "zombi_s", "zombi_s", "zombi_s", "zombi_s", "zombi_s", "zombi_s", "zombi_s", "zombi_s", "zombi_s" ],
                "typesmode": "random",
                "generator": [ 3, 4, 10, 1, 6, 9, 2, 5, 7, 8, 3, 7, 6 ],
                "generatormode": "random",
                "lazyall": 0,
                "lazyme": 4,
                "speedmode": "normal"
            }
        ],
        "62": [
            {
                "types": [ "zombi_tie_tong", "zombi_tie_tong", "zombi_tie_tong", "zombi_tie_tong", "zombi_tie_tong", "zombi_tie_tong", "zombi_tie_tong", "zombi_tie_tong" ],
                "typesmode": "random",
                "generator": [ 2, 5, 7, 10, 8, 1, 3, 6 ],
                "generatormode": "random",
                "lazyall": 0,
                "lazyme": 2,
                "speedmode": "normal"
            }
        ],
        "70": [
            {
                "types": [ "zombi_mu_tong", "zombi_mu_tong", "zombi_mu_tong", "zombi_mu_tong", "zombi_mu_tong", "zombi_mu_tong", "zombi_mu_tong", "zombi_mu_tong" ],
                "typesmode": "random",
                "generator": [ 2, 5, 7, 10, 8, 1, 3, 6 ],
                "generatormode": "random",
                "lazyall": 0,
                "lazyme": 3,
                "speedmode": "normal"
            }
        ],
        "80": [
            {
                "types": [ "zombi_mu_tong", "zombi_tie_tong", "zombi_s", "zombi_s", "zombi_mu_tong", "zombi_s", "zombi_s", "zombi_tie_tong" ],
                "typesmode": "random",
                "generator": [ 2, 9, 7, 4, 8, 1, 3, 9 ],
                "generatormode": "random",
                "lazyall": 0,
                "lazyme": 0.5,
                "speedmode": "normal"
            }
        ],
        "90": [
            {
                "types": [ "zombi_mu_tong", "zombi_tie_tong", "zombi_mu_tong", "zombi_mu_tong", "zombi_mu_tong", "zombi_tie_tong", "zombi_tie_tong", "zombi_tie_tong" ],
                "typesmode": "random",
                "generator": [ 2, 5, 7, 10, 8, 9, 4, 6 ],
                "generatormode": "random",
                "lazyall": 0,
                "lazyme": 2,
                "speedmode": "normal"
            }
        ],
        "94": [
            {
                "types": [ "zombi_s", "zombi_s", "zombi_s", "zombi_s", "zombi_s", "zombi_s", "zombi_s", "zombi_s" ],
                "typesmode": "random",
                "generator": [ 2, 10, 7, 4, 8, 1, 3, 5 ],
                "generatormode": "random",
                "lazyall": 0,
                "lazyme": 1,
                "speedmode": "normal"
            }
        ]
    },
    
    "suns": {
        "3": [
            {
                "types": [ "sun" ],
                "typesmode": "next",
                "generatormode": "random",
                "lazyme": 0
            }
        ]
    }
}